sxtg/__init__.py
sxtg/__main__.py
sxtg/bot_content/__init__.py
sxtg/bot_settings/__init__.py
sxtg/redis_connection/__init__.py
sxtg-0.1.3.dist-info/METADATA
sxtg-0.1.3.dist-info/WHEEL
sxtg-0.1.3.dist-info/top_level.txt
sxtg-0.1.3.dist-info/RECORD
