Metadata-Version: 2.1
Name: sxtg
Version: 0.1.3
Summary: aiogram util.
Author: A2RK
Author-email: atwork.igor@gmail.com
Classifier: Programming Language :: Python :: 3
Classifier: License :: OSI Approved :: MIT License
Classifier: Operating System :: OS Independent
Requires-Python: >=3.11
